{
  "schema_version": "1.0.0",
  "metric_id": "jp.cgpi.index",
  "title_ja": "企業物価指数",
  "last_updated": "2026-07-22",
  "source": "BOJ",
  "observations": [
    {
      "as_of_date": "2015-01-01",
      "still_valid_2026": true,
      "retrieved_at": "2026-07-22",
      "veritas": "✅",
      "metric_id": "jp.cgpi.index",
      "industry_slug": "national",
      "industry_name_ja": "国内企業物価指数・総平均",
      "period": "2015-01",
      "period_type": "monthly",
      "value": 100.3,
      "unit": "index_2020=100",
      "source": "日銀 時系列統計データ検索 API",
      "source_ref": "PR01 PRCG20_2200000000"
    },
    {
      "as_of_date": "2015-02-01",
      "still_valid_2026": true,
      "retrieved_at": "2026-07-22",
      "veritas": "✅",
      "metric_id": "jp.cgpi.index",
      "industry_slug": "national",
      "industry_name_ja": "国内企業物価指数・総平均",
      "period": "2015-02",
      "period_type": "monthly",
      "value": 100.3,
      "unit": "index_2020=100",
      "source": "日銀 時系列統計データ検索 API",
      "source_ref": "PR01 PRCG20_2200000000"
    },
    {
      "as_of_date": "2015-03-01",
      "still_valid_2026": true,
      "retrieved_at": "2026-07-22",
      "veritas": "✅",
      "metric_id": "jp.cgpi.index",
      "industry_slug": "national",
      "industry_name_ja": "国内企業物価指数・総平均",
      "period": "2015-03",
      "period_type": "monthly",
      "value": 100.5,
      "unit": "index_2020=100",
      "source": "日銀 時系列統計データ検索 API",
      "source_ref": "PR01 PRCG20_2200000000"
    },
    {
      "as_of_date": "2015-04-01",
      "still_valid_2026": true,
      "retrieved_at": "2026-07-22",
      "veritas": "✅",
      "metric_id": "jp.cgpi.index",
      "industry_slug": "national",
      "industry_name_ja": "国内企業物価指数・総平均",
      "period": "2015-04",
      "period_type": "monthly",
      "value": 100.5,
      "unit": "index_2020=100",
      "source": "日銀 時系列統計データ検索 API",
      "source_ref": "PR01 PRCG20_2200000000"
    },
    {
      "as_of_date": "2015-05-01",
      "still_valid_2026": true,
      "retrieved_at": "2026-07-22",
      "veritas": "✅",
      "metric_id": "jp.cgpi.index",
      "industry_slug": "national",
      "industry_name_ja": "国内企業物価指数・総平均",
      "period": "2015-05",
      "period_type": "monthly",
      "value": 100.7,
      "unit": "index_2020=100",
      "source": "日銀 時系列統計データ検索 API",
      "source_ref": "PR01 PRCG20_2200000000"
    },
    {
      "as_of_date": "2015-06-01",
      "still_valid_2026": true,
      "retrieved_at": "2026-07-22",
      "veritas": "✅",
      "metric_id": "jp.cgpi.index",
      "industry_slug": "national",
      "industry_name_ja": "国内企業物価指数・総平均",
      "period": "2015-06",
      "period_type": "monthly",
      "value": 100.6,
      "unit": "index_2020=100",
      "source": "日銀 時系列統計データ検索 API",
      "source_ref": "PR01 PRCG20_2200000000"
    },
    {
      "as_of_date": "2015-07-01",
      "still_valid_2026": true,
      "retrieved_at": "2026-07-22",
      "veritas": "✅",
      "metric_id": "jp.cgpi.index",
      "industry_slug": "national",
      "industry_name_ja": "国内企業物価指数・総平均",
      "period": "2015-07",
      "period_type": "monthly",
      "value": 100.2,
      "unit": "index_2020=100",
      "source": "日銀 時系列統計データ検索 API",
      "source_ref": "PR01 PRCG20_2200000000"
    },
    {
      "as_of_date": "2015-08-01",
      "still_valid_2026": true,
      "retrieved_at": "2026-07-22",
      "veritas": "✅",
      "metric_id": "jp.cgpi.index",
      "industry_slug": "national",
      "industry_name_ja": "国内企業物価指数・総平均",
      "period": "2015-08",
      "period_type": "monthly",
      "value": 99.5,
      "unit": "index_2020=100",
      "source": "日銀 時系列統計データ検索 API",
      "source_ref": "PR01 PRCG20_2200000000"
    },
    {
      "as_of_date": "2015-09-01",
      "still_valid_2026": true,
      "retrieved_at": "2026-07-22",
      "veritas": "✅",
      "metric_id": "jp.cgpi.index",
      "industry_slug": "national",
      "industry_name_ja": "国内企業物価指数・総平均",
      "period": "2015-09",
      "period_type": "monthly",
      "value": 99.1,
      "unit": "index_2020=100",
      "source": "日銀 時系列統計データ検索 API",
      "source_ref": "PR01 PRCG20_2200000000"
    },
    {
      "as_of_date": "2015-10-01",
      "still_valid_2026": true,
      "retrieved_at": "2026-07-22",
      "veritas": "✅",
      "metric_id": "jp.cgpi.index",
      "industry_slug": "national",
      "industry_name_ja": "国内企業物価指数・総平均",
      "period": "2015-10",
      "period_type": "monthly",
      "value": 98.4,
      "unit": "index_2020=100",
      "source": "日銀 時系列統計データ検索 API",
      "source_ref": "PR01 PRCG20_2200000000"
    },
    {
      "as_of_date": "2015-11-01",
      "still_valid_2026": true,
      "retrieved_at": "2026-07-22",
      "veritas": "✅",
      "metric_id": "jp.cgpi.index",
      "industry_slug": "national",
      "industry_name_ja": "国内企業物価指数・総平均",
      "period": "2015-11",
      "period_type": "monthly",
      "value": 98.4,
      "unit": "index_2020=100",
      "source": "日銀 時系列統計データ検索 API",
      "source_ref": "PR01 PRCG20_2200000000"
    },
    {
      "as_of_date": "2015-12-01",
      "still_valid_2026": true,
      "retrieved_at": "2026-07-22",
      "veritas": "✅",
      "metric_id": "jp.cgpi.index",
      "industry_slug": "national",
      "industry_name_ja": "国内企業物価指数・総平均",
      "period": "2015-12",
      "period_type": "monthly",
      "value": 98.0,
      "unit": "index_2020=100",
      "source": "日銀 時系列統計データ検索 API",
      "source_ref": "PR01 PRCG20_2200000000"
    },
    {
      "as_of_date": "2016-01-01",
      "still_valid_2026": true,
      "retrieved_at": "2026-07-22",
      "veritas": "✅",
      "metric_id": "jp.cgpi.index",
      "industry_slug": "national",
      "industry_name_ja": "国内企業物価指数・総平均",
      "period": "2016-01",
      "period_type": "monthly",
      "value": 96.9,
      "unit": "index_2020=100",
      "source": "日銀 時系列統計データ検索 API",
      "source_ref": "PR01 PRCG20_2200000000"
    },
    {
      "as_of_date": "2016-02-01",
      "still_valid_2026": true,
      "retrieved_at": "2026-07-22",
      "veritas": "✅",
      "metric_id": "jp.cgpi.index",
      "industry_slug": "national",
      "industry_name_ja": "国内企業物価指数・総平均",
      "period": "2016-02",
      "period_type": "monthly",
      "value": 96.6,
      "unit": "index_2020=100",
      "source": "日銀 時系列統計データ検索 API",
      "source_ref": "PR01 PRCG20_2200000000"
    },
    {
      "as_of_date": "2016-03-01",
      "still_valid_2026": true,
      "retrieved_at": "2026-07-22",
      "veritas": "✅",
      "metric_id": "jp.cgpi.index",
      "industry_slug": "national",
      "industry_name_ja": "国内企業物価指数・総平均",
      "period": "2016-03",
      "period_type": "monthly",
      "value": 96.5,
      "unit": "index_2020=100",
      "source": "日銀 時系列統計データ検索 API",
      "source_ref": "PR01 PRCG20_2200000000"
    },
    {
      "as_of_date": "2016-04-01",
      "still_valid_2026": true,
      "retrieved_at": "2026-07-22",
      "veritas": "✅",
      "metric_id": "jp.cgpi.index",
      "industry_slug": "national",
      "industry_name_ja": "国内企業物価指数・総平均",
      "period": "2016-04",
      "period_type": "monthly",
      "value": 96.1,
      "unit": "index_2020=100",
      "source": "日銀 時系列統計データ検索 API",
      "source_ref": "PR01 PRCG20_2200000000"
    },
    {
      "as_of_date": "2016-05-01",
      "still_valid_2026": true,
      "retrieved_at": "2026-07-22",
      "veritas": "✅",
      "metric_id": "jp.cgpi.index",
      "industry_slug": "national",
      "industry_name_ja": "国内企業物価指数・総平均",
      "period": "2016-05",
      "period_type": "monthly",
      "value": 96.1,
      "unit": "index_2020=100",
      "source": "日銀 時系列統計データ検索 API",
      "source_ref": "PR01 PRCG20_2200000000"
    },
    {
      "as_of_date": "2016-06-01",
      "still_valid_2026": true,
      "retrieved_at": "2026-07-22",
      "veritas": "✅",
      "metric_id": "jp.cgpi.index",
      "industry_slug": "national",
      "industry_name_ja": "国内企業物価指数・総平均",
      "period": "2016-06",
      "period_type": "monthly",
      "value": 96.1,
      "unit": "index_2020=100",
      "source": "日銀 時系列統計データ検索 API",
      "source_ref": "PR01 PRCG20_2200000000"
    },
    {
      "as_of_date": "2016-07-01",
      "still_valid_2026": true,
      "retrieved_at": "2026-07-22",
      "veritas": "✅",
      "metric_id": "jp.cgpi.index",
      "industry_slug": "national",
      "industry_name_ja": "国内企業物価指数・総平均",
      "period": "2016-07",
      "period_type": "monthly",
      "value": 96.0,
      "unit": "index_2020=100",
      "source": "日銀 時系列統計データ検索 API",
      "source_ref": "PR01 PRCG20_2200000000"
    },
    {
      "as_of_date": "2016-08-01",
      "still_valid_2026": true,
      "retrieved_at": "2026-07-22",
      "veritas": "✅",
      "metric_id": "jp.cgpi.index",
      "industry_slug": "national",
      "industry_name_ja": "国内企業物価指数・総平均",
      "period": "2016-08",
      "period_type": "monthly",
      "value": 95.7,
      "unit": "index_2020=100",
      "source": "日銀 時系列統計データ検索 API",
      "source_ref": "PR01 PRCG20_2200000000"
    },
    {
      "as_of_date": "2016-09-01",
      "still_valid_2026": true,
      "retrieved_at": "2026-07-22",
      "veritas": "✅",
      "metric_id": "jp.cgpi.index",
      "industry_slug": "national",
      "industry_name_ja": "国内企業物価指数・総平均",
      "period": "2016-09",
      "period_type": "monthly",
      "value": 95.8,
      "unit": "index_2020=100",
      "source": "日銀 時系列統計データ検索 API",
      "source_ref": "PR01 PRCG20_2200000000"
    },
    {
      "as_of_date": "2016-10-01",
      "still_valid_2026": true,
      "retrieved_at": "2026-07-22",
      "veritas": "✅",
      "metric_id": "jp.cgpi.index",
      "industry_slug": "national",
      "industry_name_ja": "国内企業物価指数・総平均",
      "period": "2016-10",
      "period_type": "monthly",
      "value": 95.7,
      "unit": "index_2020=100",
      "source": "日銀 時系列統計データ検索 API",
      "source_ref": "PR01 PRCG20_2200000000"
    },
    {
      "as_of_date": "2016-11-01",
      "still_valid_2026": true,
      "retrieved_at": "2026-07-22",
      "veritas": "✅",
      "metric_id": "jp.cgpi.index",
      "industry_slug": "national",
      "industry_name_ja": "国内企業物価指数・総平均",
      "period": "2016-11",
      "period_type": "monthly",
      "value": 96.1,
      "unit": "index_2020=100",
      "source": "日銀 時系列統計データ検索 API",
      "source_ref": "PR01 PRCG20_2200000000"
    },
    {
      "as_of_date": "2016-12-01",
      "still_valid_2026": true,
      "retrieved_at": "2026-07-22",
      "veritas": "✅",
      "metric_id": "jp.cgpi.index",
      "industry_slug": "national",
      "industry_name_ja": "国内企業物価指数・総平均",
      "period": "2016-12",
      "period_type": "monthly",
      "value": 96.8,
      "unit": "index_2020=100",
      "source": "日銀 時系列統計データ検索 API",
      "source_ref": "PR01 PRCG20_2200000000"
    },
    {
      "as_of_date": "2017-01-01",
      "still_valid_2026": true,
      "retrieved_at": "2026-07-22",
      "veritas": "✅",
      "metric_id": "jp.cgpi.index",
      "industry_slug": "national",
      "industry_name_ja": "国内企業物価指数・総平均",
      "period": "2017-01",
      "period_type": "monthly",
      "value": 97.4,
      "unit": "index_2020=100",
      "source": "日銀 時系列統計データ検索 API",
      "source_ref": "PR01 PRCG20_2200000000"
    },
    {
      "as_of_date": "2017-02-01",
      "still_valid_2026": true,
      "retrieved_at": "2026-07-22",
      "veritas": "✅",
      "metric_id": "jp.cgpi.index",
      "industry_slug": "national",
      "industry_name_ja": "国内企業物価指数・総平均",
      "period": "2017-02",
      "period_type": "monthly",
      "value": 97.6,
      "unit": "index_2020=100",
      "source": "日銀 時系列統計データ検索 API",
      "source_ref": "PR01 PRCG20_2200000000"
    },
    {
      "as_of_date": "2017-03-01",
      "still_valid_2026": true,
      "retrieved_at": "2026-07-22",
      "veritas": "✅",
      "metric_id": "jp.cgpi.index",
      "industry_slug": "national",
      "industry_name_ja": "国内企業物価指数・総平均",
      "period": "2017-03",
      "period_type": "monthly",
      "value": 97.9,
      "unit": "index_2020=100",
      "source": "日銀 時系列統計データ検索 API",
      "source_ref": "PR01 PRCG20_2200000000"
    },
    {
      "as_of_date": "2017-04-01",
      "still_valid_2026": true,
      "retrieved_at": "2026-07-22",
      "veritas": "✅",
      "metric_id": "jp.cgpi.index",
      "industry_slug": "national",
      "industry_name_ja": "国内企業物価指数・総平均",
      "period": "2017-04",
      "period_type": "monthly",
      "value": 98.1,
      "unit": "index_2020=100",
      "source": "日銀 時系列統計データ検索 API",
      "source_ref": "PR01 PRCG20_2200000000"
    },
    {
      "as_of_date": "2017-05-01",
      "still_valid_2026": true,
      "retrieved_at": "2026-07-22",
      "veritas": "✅",
      "metric_id": "jp.cgpi.index",
      "industry_slug": "national",
      "industry_name_ja": "国内企業物価指数・総平均",
      "period": "2017-05",
      "period_type": "monthly",
      "value": 98.1,
      "unit": "index_2020=100",
      "source": "日銀 時系列統計データ検索 API",
      "source_ref": "PR01 PRCG20_2200000000"
    },
    {
      "as_of_date": "2017-06-01",
      "still_valid_2026": true,
      "retrieved_at": "2026-07-22",
      "veritas": "✅",
      "metric_id": "jp.cgpi.index",
      "industry_slug": "national",
      "industry_name_ja": "国内企業物価指数・総平均",
      "period": "2017-06",
      "period_type": "monthly",
      "value": 98.2,
      "unit": "index_2020=100",
      "source": "日銀 時系列統計データ検索 API",
      "source_ref": "PR01 PRCG20_2200000000"
    },
    {
      "as_of_date": "2017-07-01",
      "still_valid_2026": true,
      "retrieved_at": "2026-07-22",
      "veritas": "✅",
      "metric_id": "jp.cgpi.index",
      "industry_slug": "national",
      "industry_name_ja": "国内企業物価指数・総平均",
      "period": "2017-07",
      "period_type": "monthly",
      "value": 98.4,
      "unit": "index_2020=100",
      "source": "日銀 時系列統計データ検索 API",
      "source_ref": "PR01 PRCG20_2200000000"
    },
    {
      "as_of_date": "2017-08-01",
      "still_valid_2026": true,
      "retrieved_at": "2026-07-22",
      "veritas": "✅",
      "metric_id": "jp.cgpi.index",
      "industry_slug": "national",
      "industry_name_ja": "国内企業物価指数・総平均",
      "period": "2017-08",
      "period_type": "monthly",
      "value": 98.4,
      "unit": "index_2020=100",
      "source": "日銀 時系列統計データ検索 API",
      "source_ref": "PR01 PRCG20_2200000000"
    },
    {
      "as_of_date": "2017-09-01",
      "still_valid_2026": true,
      "retrieved_at": "2026-07-22",
      "veritas": "✅",
      "metric_id": "jp.cgpi.index",
      "industry_slug": "national",
      "industry_name_ja": "国内企業物価指数・総平均",
      "period": "2017-09",
      "period_type": "monthly",
      "value": 98.7,
      "unit": "index_2020=100",
      "source": "日銀 時系列統計データ検索 API",
      "source_ref": "PR01 PRCG20_2200000000"
    },
    {
      "as_of_date": "2017-10-01",
      "still_valid_2026": true,
      "retrieved_at": "2026-07-22",
      "veritas": "✅",
      "metric_id": "jp.cgpi.index",
      "industry_slug": "national",
      "industry_name_ja": "国内企業物価指数・総平均",
      "period": "2017-10",
      "period_type": "monthly",
      "value": 99.1,
      "unit": "index_2020=100",
      "source": "日銀 時系列統計データ検索 API",
      "source_ref": "PR01 PRCG20_2200000000"
    },
    {
      "as_of_date": "2017-11-01",
      "still_valid_2026": true,
      "retrieved_at": "2026-07-22",
      "veritas": "✅",
      "metric_id": "jp.cgpi.index",
      "industry_slug": "national",
      "industry_name_ja": "国内企業物価指数・総平均",
      "period": "2017-11",
      "period_type": "monthly",
      "value": 99.5,
      "unit": "index_2020=100",
      "source": "日銀 時系列統計データ検索 API",
      "source_ref": "PR01 PRCG20_2200000000"
    },
    {
      "as_of_date": "2017-12-01",
      "still_valid_2026": true,
      "retrieved_at": "2026-07-22",
      "veritas": "✅",
      "metric_id": "jp.cgpi.index",
      "industry_slug": "national",
      "industry_name_ja": "国内企業物価指数・総平均",
      "period": "2017-12",
      "period_type": "monthly",
      "value": 99.7,
      "unit": "index_2020=100",
      "source": "日銀 時系列統計データ検索 API",
      "source_ref": "PR01 PRCG20_2200000000"
    },
    {
      "as_of_date": "2018-01-01",
      "still_valid_2026": true,
      "retrieved_at": "2026-07-22",
      "veritas": "✅",
      "metric_id": "jp.cgpi.index",
      "industry_slug": "national",
      "industry_name_ja": "国内企業物価指数・総平均",
      "period": "2018-01",
      "period_type": "monthly",
      "value": 100.0,
      "unit": "index_2020=100",
      "source": "日銀 時系列統計データ検索 API",
      "source_ref": "PR01 PRCG20_2200000000"
    },
    {
      "as_of_date": "2018-02-01",
      "still_valid_2026": true,
      "retrieved_at": "2026-07-22",
      "veritas": "✅",
      "metric_id": "jp.cgpi.index",
      "industry_slug": "national",
      "industry_name_ja": "国内企業物価指数・総平均",
      "period": "2018-02",
      "period_type": "monthly",
      "value": 100.0,
      "unit": "index_2020=100",
      "source": "日銀 時系列統計データ検索 API",
      "source_ref": "PR01 PRCG20_2200000000"
    },
    {
      "as_of_date": "2018-03-01",
      "still_valid_2026": true,
      "retrieved_at": "2026-07-22",
      "veritas": "✅",
      "metric_id": "jp.cgpi.index",
      "industry_slug": "national",
      "industry_name_ja": "国内企業物価指数・総平均",
      "period": "2018-03",
      "period_type": "monthly",
      "value": 99.9,
      "unit": "index_2020=100",
      "source": "日銀 時系列統計データ検索 API",
      "source_ref": "PR01 PRCG20_2200000000"
    },
    {
      "as_of_date": "2018-04-01",
      "still_valid_2026": true,
      "retrieved_at": "2026-07-22",
      "veritas": "✅",
      "metric_id": "jp.cgpi.index",
      "industry_slug": "national",
      "industry_name_ja": "国内企業物価指数・総平均",
      "period": "2018-04",
      "period_type": "monthly",
      "value": 100.3,
      "unit": "index_2020=100",
      "source": "日銀 時系列統計データ検索 API",
      "source_ref": "PR01 PRCG20_2200000000"
    },
    {
      "as_of_date": "2018-05-01",
      "still_valid_2026": true,
      "retrieved_at": "2026-07-22",
      "veritas": "✅",
      "metric_id": "jp.cgpi.index",
      "industry_slug": "national",
      "industry_name_ja": "国内企業物価指数・総平均",
      "period": "2018-05",
      "period_type": "monthly",
      "value": 100.8,
      "unit": "index_2020=100",
      "source": "日銀 時系列統計データ検索 API",
      "source_ref": "PR01 PRCG20_2200000000"
    },
    {
      "as_of_date": "2018-06-01",
      "still_valid_2026": true,
      "retrieved_at": "2026-07-22",
      "veritas": "✅",
      "metric_id": "jp.cgpi.index",
      "industry_slug": "national",
      "industry_name_ja": "国内企業物価指数・総平均",
      "period": "2018-06",
      "period_type": "monthly",
      "value": 101.1,
      "unit": "index_2020=100",
      "source": "日銀 時系列統計データ検索 API",
      "source_ref": "PR01 PRCG20_2200000000"
    },
    {
      "as_of_date": "2018-07-01",
      "still_valid_2026": true,
      "retrieved_at": "2026-07-22",
      "veritas": "✅",
      "metric_id": "jp.cgpi.index",
      "industry_slug": "national",
      "industry_name_ja": "国内企業物価指数・総平均",
      "period": "2018-07",
      "period_type": "monthly",
      "value": 101.5,
      "unit": "index_2020=100",
      "source": "日銀 時系列統計データ検索 API",
      "source_ref": "PR01 PRCG20_2200000000"
    },
    {
      "as_of_date": "2018-08-01",
      "still_valid_2026": true,
      "retrieved_at": "2026-07-22",
      "veritas": "✅",
      "metric_id": "jp.cgpi.index",
      "industry_slug": "national",
      "industry_name_ja": "国内企業物価指数・総平均",
      "period": "2018-08",
      "period_type": "monthly",
      "value": 101.5,
      "unit": "index_2020=100",
      "source": "日銀 時系列統計データ検索 API",
      "source_ref": "PR01 PRCG20_2200000000"
    },
    {
      "as_of_date": "2018-09-01",
      "still_valid_2026": true,
      "retrieved_at": "2026-07-22",
      "veritas": "✅",
      "metric_id": "jp.cgpi.index",
      "industry_slug": "national",
      "industry_name_ja": "国内企業物価指数・総平均",
      "period": "2018-09",
      "period_type": "monthly",
      "value": 101.7,
      "unit": "index_2020=100",
      "source": "日銀 時系列統計データ検索 API",
      "source_ref": "PR01 PRCG20_2200000000"
    },
    {
      "as_of_date": "2018-10-01",
      "still_valid_2026": true,
      "retrieved_at": "2026-07-22",
      "veritas": "✅",
      "metric_id": "jp.cgpi.index",
      "industry_slug": "national",
      "industry_name_ja": "国内企業物価指数・総平均",
      "period": "2018-10",
      "period_type": "monthly",
      "value": 102.1,
      "unit": "index_2020=100",
      "source": "日銀 時系列統計データ検索 API",
      "source_ref": "PR01 PRCG20_2200000000"
    },
    {
      "as_of_date": "2018-11-01",
      "still_valid_2026": true,
      "retrieved_at": "2026-07-22",
      "veritas": "✅",
      "metric_id": "jp.cgpi.index",
      "industry_slug": "national",
      "industry_name_ja": "国内企業物価指数・総平均",
      "period": "2018-11",
      "period_type": "monthly",
      "value": 101.7,
      "unit": "index_2020=100",
      "source": "日銀 時系列統計データ検索 API",
      "source_ref": "PR01 PRCG20_2200000000"
    },
    {
      "as_of_date": "2018-12-01",
      "still_valid_2026": true,
      "retrieved_at": "2026-07-22",
      "veritas": "✅",
      "metric_id": "jp.cgpi.index",
      "industry_slug": "national",
      "industry_name_ja": "国内企業物価指数・総平均",
      "period": "2018-12",
      "period_type": "monthly",
      "value": 101.1,
      "unit": "index_2020=100",
      "source": "日銀 時系列統計データ検索 API",
      "source_ref": "PR01 PRCG20_2200000000"
    },
    {
      "as_of_date": "2019-01-01",
      "still_valid_2026": true,
      "retrieved_at": "2026-07-22",
      "veritas": "✅",
      "metric_id": "jp.cgpi.index",
      "industry_slug": "national",
      "industry_name_ja": "国内企業物価指数・総平均",
      "period": "2019-01",
      "period_type": "monthly",
      "value": 100.5,
      "unit": "index_2020=100",
      "source": "日銀 時系列統計データ検索 API",
      "source_ref": "PR01 PRCG20_2200000000"
    },
    {
      "as_of_date": "2019-02-01",
      "still_valid_2026": true,
      "retrieved_at": "2026-07-22",
      "veritas": "✅",
      "metric_id": "jp.cgpi.index",
      "industry_slug": "national",
      "industry_name_ja": "国内企業物価指数・総平均",
      "period": "2019-02",
      "period_type": "monthly",
      "value": 100.9,
      "unit": "index_2020=100",
      "source": "日銀 時系列統計データ検索 API",
      "source_ref": "PR01 PRCG20_2200000000"
    },
    {
      "as_of_date": "2019-03-01",
      "still_valid_2026": true,
      "retrieved_at": "2026-07-22",
      "veritas": "✅",
      "metric_id": "jp.cgpi.index",
      "industry_slug": "national",
      "industry_name_ja": "国内企業物価指数・総平均",
      "period": "2019-03",
      "period_type": "monthly",
      "value": 101.2,
      "unit": "index_2020=100",
      "source": "日銀 時系列統計データ検索 API",
      "source_ref": "PR01 PRCG20_2200000000"
    },
    {
      "as_of_date": "2019-04-01",
      "still_valid_2026": true,
      "retrieved_at": "2026-07-22",
      "veritas": "✅",
      "metric_id": "jp.cgpi.index",
      "industry_slug": "national",
      "industry_name_ja": "国内企業物価指数・総平均",
      "period": "2019-04",
      "period_type": "monthly",
      "value": 101.6,
      "unit": "index_2020=100",
      "source": "日銀 時系列統計データ検索 API",
      "source_ref": "PR01 PRCG20_2200000000"
    },
    {
      "as_of_date": "2019-05-01",
      "still_valid_2026": true,
      "retrieved_at": "2026-07-22",
      "veritas": "✅",
      "metric_id": "jp.cgpi.index",
      "industry_slug": "national",
      "industry_name_ja": "国内企業物価指数・総平均",
      "period": "2019-05",
      "period_type": "monthly",
      "value": 101.4,
      "unit": "index_2020=100",
      "source": "日銀 時系列統計データ検索 API",
      "source_ref": "PR01 PRCG20_2200000000"
    },
    {
      "as_of_date": "2019-06-01",
      "still_valid_2026": true,
      "retrieved_at": "2026-07-22",
      "veritas": "✅",
      "metric_id": "jp.cgpi.index",
      "industry_slug": "national",
      "industry_name_ja": "国内企業物価指数・総平均",
      "period": "2019-06",
      "period_type": "monthly",
      "value": 100.9,
      "unit": "index_2020=100",
      "source": "日銀 時系列統計データ検索 API",
      "source_ref": "PR01 PRCG20_2200000000"
    },
    {
      "as_of_date": "2019-07-01",
      "still_valid_2026": true,
      "retrieved_at": "2026-07-22",
      "veritas": "✅",
      "metric_id": "jp.cgpi.index",
      "industry_slug": "national",
      "industry_name_ja": "国内企業物価指数・総平均",
      "period": "2019-07",
      "period_type": "monthly",
      "value": 100.8,
      "unit": "index_2020=100",
      "source": "日銀 時系列統計データ検索 API",
      "source_ref": "PR01 PRCG20_2200000000"
    },
    {
      "as_of_date": "2019-08-01",
      "still_valid_2026": true,
      "retrieved_at": "2026-07-22",
      "veritas": "✅",
      "metric_id": "jp.cgpi.index",
      "industry_slug": "national",
      "industry_name_ja": "国内企業物価指数・総平均",
      "period": "2019-08",
      "period_type": "monthly",
      "value": 100.6,
      "unit": "index_2020=100",
      "source": "日銀 時系列統計データ検索 API",
      "source_ref": "PR01 PRCG20_2200000000"
    },
    {
      "as_of_date": "2019-09-01",
      "still_valid_2026": true,
      "retrieved_at": "2026-07-22",
      "veritas": "✅",
      "metric_id": "jp.cgpi.index",
      "industry_slug": "national",
      "industry_name_ja": "国内企業物価指数・総平均",
      "period": "2019-09",
      "period_type": "monthly",
      "value": 100.6,
      "unit": "index_2020=100",
      "source": "日銀 時系列統計データ検索 API",
      "source_ref": "PR01 PRCG20_2200000000"
    },
    {
      "as_of_date": "2019-10-01",
      "still_valid_2026": true,
      "retrieved_at": "2026-07-22",
      "veritas": "✅",
      "metric_id": "jp.cgpi.index",
      "industry_slug": "national",
      "industry_name_ja": "国内企業物価指数・総平均",
      "period": "2019-10",
      "period_type": "monthly",
      "value": 101.7,
      "unit": "index_2020=100",
      "source": "日銀 時系列統計データ検索 API",
      "source_ref": "PR01 PRCG20_2200000000"
    },
    {
      "as_of_date": "2019-11-01",
      "still_valid_2026": true,
      "retrieved_at": "2026-07-22",
      "veritas": "✅",
      "metric_id": "jp.cgpi.index",
      "industry_slug": "national",
      "industry_name_ja": "国内企業物価指数・総平均",
      "period": "2019-11",
      "period_type": "monthly",
      "value": 101.8,
      "unit": "index_2020=100",
      "source": "日銀 時系列統計データ検索 API",
      "source_ref": "PR01 PRCG20_2200000000"
    },
    {
      "as_of_date": "2019-12-01",
      "still_valid_2026": true,
      "retrieved_at": "2026-07-22",
      "veritas": "✅",
      "metric_id": "jp.cgpi.index",
      "industry_slug": "national",
      "industry_name_ja": "国内企業物価指数・総平均",
      "period": "2019-12",
      "period_type": "monthly",
      "value": 102.0,
      "unit": "index_2020=100",
      "source": "日銀 時系列統計データ検索 API",
      "source_ref": "PR01 PRCG20_2200000000"
    },
    {
      "as_of_date": "2020-01-01",
      "still_valid_2026": true,
      "retrieved_at": "2026-07-22",
      "veritas": "✅",
      "metric_id": "jp.cgpi.index",
      "industry_slug": "national",
      "industry_name_ja": "国内企業物価指数・総平均",
      "period": "2020-01",
      "period_type": "monthly",
      "value": 102.1,
      "unit": "index_2020=100",
      "source": "日銀 時系列統計データ検索 API",
      "source_ref": "PR01 PRCG20_2200000000"
    },
    {
      "as_of_date": "2020-02-01",
      "still_valid_2026": true,
      "retrieved_at": "2026-07-22",
      "veritas": "✅",
      "metric_id": "jp.cgpi.index",
      "industry_slug": "national",
      "industry_name_ja": "国内企業物価指数・総平均",
      "period": "2020-02",
      "period_type": "monthly",
      "value": 101.7,
      "unit": "index_2020=100",
      "source": "日銀 時系列統計データ検索 API",
      "source_ref": "PR01 PRCG20_2200000000"
    },
    {
      "as_of_date": "2020-03-01",
      "still_valid_2026": true,
      "retrieved_at": "2026-07-22",
      "veritas": "✅",
      "metric_id": "jp.cgpi.index",
      "industry_slug": "national",
      "industry_name_ja": "国内企業物価指数・総平均",
      "period": "2020-03",
      "period_type": "monthly",
      "value": 100.8,
      "unit": "index_2020=100",
      "source": "日銀 時系列統計データ検索 API",
      "source_ref": "PR01 PRCG20_2200000000"
    },
    {
      "as_of_date": "2020-04-01",
      "still_valid_2026": true,
      "retrieved_at": "2026-07-22",
      "veritas": "✅",
      "metric_id": "jp.cgpi.index",
      "industry_slug": "national",
      "industry_name_ja": "国内企業物価指数・総平均",
      "period": "2020-04",
      "period_type": "monthly",
      "value": 99.2,
      "unit": "index_2020=100",
      "source": "日銀 時系列統計データ検索 API",
      "source_ref": "PR01 PRCG20_2200000000"
    },
    {
      "as_of_date": "2020-05-01",
      "still_valid_2026": true,
      "retrieved_at": "2026-07-22",
      "veritas": "✅",
      "metric_id": "jp.cgpi.index",
      "industry_slug": "national",
      "industry_name_ja": "国内企業物価指数・総平均",
      "period": "2020-05",
      "period_type": "monthly",
      "value": 98.7,
      "unit": "index_2020=100",
      "source": "日銀 時系列統計データ検索 API",
      "source_ref": "PR01 PRCG20_2200000000"
    },
    {
      "as_of_date": "2020-06-01",
      "still_valid_2026": true,
      "retrieved_at": "2026-07-22",
      "veritas": "✅",
      "metric_id": "jp.cgpi.index",
      "industry_slug": "national",
      "industry_name_ja": "国内企業物価指数・総平均",
      "period": "2020-06",
      "period_type": "monthly",
      "value": 99.3,
      "unit": "index_2020=100",
      "source": "日銀 時系列統計データ検索 API",
      "source_ref": "PR01 PRCG20_2200000000"
    },
    {
      "as_of_date": "2020-07-01",
      "still_valid_2026": true,
      "retrieved_at": "2026-07-22",
      "veritas": "✅",
      "metric_id": "jp.cgpi.index",
      "industry_slug": "national",
      "industry_name_ja": "国内企業物価指数・総平均",
      "period": "2020-07",
      "period_type": "monthly",
      "value": 99.8,
      "unit": "index_2020=100",
      "source": "日銀 時系列統計データ検索 API",
      "source_ref": "PR01 PRCG20_2200000000"
    },
    {
      "as_of_date": "2020-08-01",
      "still_valid_2026": true,
      "retrieved_at": "2026-07-22",
      "veritas": "✅",
      "metric_id": "jp.cgpi.index",
      "industry_slug": "national",
      "industry_name_ja": "国内企業物価指数・総平均",
      "period": "2020-08",
      "period_type": "monthly",
      "value": 99.9,
      "unit": "index_2020=100",
      "source": "日銀 時系列統計データ検索 API",
      "source_ref": "PR01 PRCG20_2200000000"
    },
    {
      "as_of_date": "2020-09-01",
      "still_valid_2026": true,
      "retrieved_at": "2026-07-22",
      "veritas": "✅",
      "metric_id": "jp.cgpi.index",
      "industry_slug": "national",
      "industry_name_ja": "国内企業物価指数・総平均",
      "period": "2020-09",
      "period_type": "monthly",
      "value": 99.8,
      "unit": "index_2020=100",
      "source": "日銀 時系列統計データ検索 API",
      "source_ref": "PR01 PRCG20_2200000000"
    },
    {
      "as_of_date": "2020-10-01",
      "still_valid_2026": true,
      "retrieved_at": "2026-07-22",
      "veritas": "✅",
      "metric_id": "jp.cgpi.index",
      "industry_slug": "national",
      "industry_name_ja": "国内企業物価指数・総平均",
      "period": "2020-10",
      "period_type": "monthly",
      "value": 99.5,
      "unit": "index_2020=100",
      "source": "日銀 時系列統計データ検索 API",
      "source_ref": "PR01 PRCG20_2200000000"
    },
    {
      "as_of_date": "2020-11-01",
      "still_valid_2026": true,
      "retrieved_at": "2026-07-22",
      "veritas": "✅",
      "metric_id": "jp.cgpi.index",
      "industry_slug": "national",
      "industry_name_ja": "国内企業物価指数・総平均",
      "period": "2020-11",
      "period_type": "monthly",
      "value": 99.4,
      "unit": "index_2020=100",
      "source": "日銀 時系列統計データ検索 API",
      "source_ref": "PR01 PRCG20_2200000000"
    },
    {
      "as_of_date": "2020-12-01",
      "still_valid_2026": true,
      "retrieved_at": "2026-07-22",
      "veritas": "✅",
      "metric_id": "jp.cgpi.index",
      "industry_slug": "national",
      "industry_name_ja": "国内企業物価指数・総平均",
      "period": "2020-12",
      "period_type": "monthly",
      "value": 99.8,
      "unit": "index_2020=100",
      "source": "日銀 時系列統計データ検索 API",
      "source_ref": "PR01 PRCG20_2200000000"
    },
    {
      "as_of_date": "2021-01-01",
      "still_valid_2026": true,
      "retrieved_at": "2026-07-22",
      "veritas": "✅",
      "metric_id": "jp.cgpi.index",
      "industry_slug": "national",
      "industry_name_ja": "国内企業物価指数・総平均",
      "period": "2021-01",
      "period_type": "monthly",
      "value": 100.3,
      "unit": "index_2020=100",
      "source": "日銀 時系列統計データ検索 API",
      "source_ref": "PR01 PRCG20_2200000000"
    },
    {
      "as_of_date": "2021-02-01",
      "still_valid_2026": true,
      "retrieved_at": "2026-07-22",
      "veritas": "✅",
      "metric_id": "jp.cgpi.index",
      "industry_slug": "national",
      "industry_name_ja": "国内企業物価指数・総平均",
      "period": "2021-02",
      "period_type": "monthly",
      "value": 100.8,
      "unit": "index_2020=100",
      "source": "日銀 時系列統計データ検索 API",
      "source_ref": "PR01 PRCG20_2200000000"
    },
    {
      "as_of_date": "2021-03-01",
      "still_valid_2026": true,
      "retrieved_at": "2026-07-22",
      "veritas": "✅",
      "metric_id": "jp.cgpi.index",
      "industry_slug": "national",
      "industry_name_ja": "国内企業物価指数・総平均",
      "period": "2021-03",
      "period_type": "monthly",
      "value": 101.8,
      "unit": "index_2020=100",
      "source": "日銀 時系列統計データ検索 API",
      "source_ref": "PR01 PRCG20_2200000000"
    },
    {
      "as_of_date": "2021-04-01",
      "still_valid_2026": true,
      "retrieved_at": "2026-07-22",
      "veritas": "✅",
      "metric_id": "jp.cgpi.index",
      "industry_slug": "national",
      "industry_name_ja": "国内企業物価指数・総平均",
      "period": "2021-04",
      "period_type": "monthly",
      "value": 103.0,
      "unit": "index_2020=100",
      "source": "日銀 時系列統計データ検索 API",
      "source_ref": "PR01 PRCG20_2200000000"
    },
    {
      "as_of_date": "2021-05-01",
      "still_valid_2026": true,
      "retrieved_at": "2026-07-22",
      "veritas": "✅",
      "metric_id": "jp.cgpi.index",
      "industry_slug": "national",
      "industry_name_ja": "国内企業物価指数・総平均",
      "period": "2021-05",
      "period_type": "monthly",
      "value": 103.6,
      "unit": "index_2020=100",
      "source": "日銀 時系列統計データ検索 API",
      "source_ref": "PR01 PRCG20_2200000000"
    },
    {
      "as_of_date": "2021-06-01",
      "still_valid_2026": true,
      "retrieved_at": "2026-07-22",
      "veritas": "✅",
      "metric_id": "jp.cgpi.index",
      "industry_slug": "national",
      "industry_name_ja": "国内企業物価指数・総平均",
      "period": "2021-06",
      "period_type": "monthly",
      "value": 104.3,
      "unit": "index_2020=100",
      "source": "日銀 時系列統計データ検索 API",
      "source_ref": "PR01 PRCG20_2200000000"
    },
    {
      "as_of_date": "2021-07-01",
      "still_valid_2026": true,
      "retrieved_at": "2026-07-22",
      "veritas": "✅",
      "metric_id": "jp.cgpi.index",
      "industry_slug": "national",
      "industry_name_ja": "国内企業物価指数・総平均",
      "period": "2021-07",
      "period_type": "monthly",
      "value": 105.4,
      "unit": "index_2020=100",
      "source": "日銀 時系列統計データ検索 API",
      "source_ref": "PR01 PRCG20_2200000000"
    },
    {
      "as_of_date": "2021-08-01",
      "still_valid_2026": true,
      "retrieved_at": "2026-07-22",
      "veritas": "✅",
      "metric_id": "jp.cgpi.index",
      "industry_slug": "national",
      "industry_name_ja": "国内企業物価指数・総平均",
      "period": "2021-08",
      "period_type": "monthly",
      "value": 105.6,
      "unit": "index_2020=100",
      "source": "日銀 時系列統計データ検索 API",
      "source_ref": "PR01 PRCG20_2200000000"
    },
    {
      "as_of_date": "2021-09-01",
      "still_valid_2026": true,
      "retrieved_at": "2026-07-22",
      "veritas": "✅",
      "metric_id": "jp.cgpi.index",
      "industry_slug": "national",
      "industry_name_ja": "国内企業物価指数・総平均",
      "period": "2021-09",
      "period_type": "monthly",
      "value": 106.0,
      "unit": "index_2020=100",
      "source": "日銀 時系列統計データ検索 API",
      "source_ref": "PR01 PRCG20_2200000000"
    },
    {
      "as_of_date": "2021-10-01",
      "still_valid_2026": true,
      "retrieved_at": "2026-07-22",
      "veritas": "✅",
      "metric_id": "jp.cgpi.index",
      "industry_slug": "national",
      "industry_name_ja": "国内企業物価指数・総平均",
      "period": "2021-10",
      "period_type": "monthly",
      "value": 107.7,
      "unit": "index_2020=100",
      "source": "日銀 時系列統計データ検索 API",
      "source_ref": "PR01 PRCG20_2200000000"
    },
    {
      "as_of_date": "2021-11-01",
      "still_valid_2026": true,
      "retrieved_at": "2026-07-22",
      "veritas": "✅",
      "metric_id": "jp.cgpi.index",
      "industry_slug": "national",
      "industry_name_ja": "国内企業物価指数・総平均",
      "period": "2021-11",
      "period_type": "monthly",
      "value": 108.4,
      "unit": "index_2020=100",
      "source": "日銀 時系列統計データ検索 API",
      "source_ref": "PR01 PRCG20_2200000000"
    },
    {
      "as_of_date": "2021-12-01",
      "still_valid_2026": true,
      "retrieved_at": "2026-07-22",
      "veritas": "✅",
      "metric_id": "jp.cgpi.index",
      "industry_slug": "national",
      "industry_name_ja": "国内企業物価指数・総平均",
      "period": "2021-12",
      "period_type": "monthly",
      "value": 108.4,
      "unit": "index_2020=100",
      "source": "日銀 時系列統計データ検索 API",
      "source_ref": "PR01 PRCG20_2200000000"
    },
    {
      "as_of_date": "2022-01-01",
      "still_valid_2026": true,
      "retrieved_at": "2026-07-22",
      "veritas": "✅",
      "metric_id": "jp.cgpi.index",
      "industry_slug": "national",
      "industry_name_ja": "国内企業物価指数・総平均",
      "period": "2022-01",
      "period_type": "monthly",
      "value": 109.5,
      "unit": "index_2020=100",
      "source": "日銀 時系列統計データ検索 API",
      "source_ref": "PR01 PRCG20_2200000000"
    },
    {
      "as_of_date": "2022-02-01",
      "still_valid_2026": true,
      "retrieved_at": "2026-07-22",
      "veritas": "✅",
      "metric_id": "jp.cgpi.index",
      "industry_slug": "national",
      "industry_name_ja": "国内企業物価指数・総平均",
      "period": "2022-02",
      "period_type": "monthly",
      "value": 110.4,
      "unit": "index_2020=100",
      "source": "日銀 時系列統計データ検索 API",
      "source_ref": "PR01 PRCG20_2200000000"
    },
    {
      "as_of_date": "2022-03-01",
      "still_valid_2026": true,
      "retrieved_at": "2026-07-22",
      "veritas": "✅",
      "metric_id": "jp.cgpi.index",
      "industry_slug": "national",
      "industry_name_ja": "国内企業物価指数・総平均",
      "period": "2022-03",
      "period_type": "monthly",
      "value": 111.5,
      "unit": "index_2020=100",
      "source": "日銀 時系列統計データ検索 API",
      "source_ref": "PR01 PRCG20_2200000000"
    },
    {
      "as_of_date": "2022-04-01",
      "still_valid_2026": true,
      "retrieved_at": "2026-07-22",
      "veritas": "✅",
      "metric_id": "jp.cgpi.index",
      "industry_slug": "national",
      "industry_name_ja": "国内企業物価指数・総平均",
      "period": "2022-04",
      "period_type": "monthly",
      "value": 113.5,
      "unit": "index_2020=100",
      "source": "日銀 時系列統計データ検索 API",
      "source_ref": "PR01 PRCG20_2200000000"
    },
    {
      "as_of_date": "2022-05-01",
      "still_valid_2026": true,
      "retrieved_at": "2026-07-22",
      "veritas": "✅",
      "metric_id": "jp.cgpi.index",
      "industry_slug": "national",
      "industry_name_ja": "国内企業物価指数・総平均",
      "period": "2022-05",
      "period_type": "monthly",
      "value": 113.5,
      "unit": "index_2020=100",
      "source": "日銀 時系列統計データ検索 API",
      "source_ref": "PR01 PRCG20_2200000000"
    },
    {
      "as_of_date": "2022-06-01",
      "still_valid_2026": true,
      "retrieved_at": "2026-07-22",
      "veritas": "✅",
      "metric_id": "jp.cgpi.index",
      "industry_slug": "national",
      "industry_name_ja": "国内企業物価指数・総平均",
      "period": "2022-06",
      "period_type": "monthly",
      "value": 114.5,
      "unit": "index_2020=100",
      "source": "日銀 時系列統計データ検索 API",
      "source_ref": "PR01 PRCG20_2200000000"
    },
    {
      "as_of_date": "2022-07-01",
      "still_valid_2026": true,
      "retrieved_at": "2026-07-22",
      "veritas": "✅",
      "metric_id": "jp.cgpi.index",
      "industry_slug": "national",
      "industry_name_ja": "国内企業物価指数・総平均",
      "period": "2022-07",
      "period_type": "monthly",
      "value": 115.4,
      "unit": "index_2020=100",
      "source": "日銀 時系列統計データ検索 API",
      "source_ref": "PR01 PRCG20_2200000000"
    },
    {
      "as_of_date": "2022-08-01",
      "still_valid_2026": true,
      "retrieved_at": "2026-07-22",
      "veritas": "✅",
      "metric_id": "jp.cgpi.index",
      "industry_slug": "national",
      "industry_name_ja": "国内企業物価指数・総平均",
      "period": "2022-08",
      "period_type": "monthly",
      "value": 115.9,
      "unit": "index_2020=100",
      "source": "日銀 時系列統計データ検索 API",
      "source_ref": "PR01 PRCG20_2200000000"
    },
    {
      "as_of_date": "2022-09-01",
      "still_valid_2026": true,
      "retrieved_at": "2026-07-22",
      "veritas": "✅",
      "metric_id": "jp.cgpi.index",
      "industry_slug": "national",
      "industry_name_ja": "国内企業物価指数・総平均",
      "period": "2022-09",
      "period_type": "monthly",
      "value": 117.0,
      "unit": "index_2020=100",
      "source": "日銀 時系列統計データ検索 API",
      "source_ref": "PR01 PRCG20_2200000000"
    },
    {
      "as_of_date": "2022-10-01",
      "still_valid_2026": true,
      "retrieved_at": "2026-07-22",
      "veritas": "✅",
      "metric_id": "jp.cgpi.index",
      "industry_slug": "national",
      "industry_name_ja": "国内企業物価指数・総平均",
      "period": "2022-10",
      "period_type": "monthly",
      "value": 118.2,
      "unit": "index_2020=100",
      "source": "日銀 時系列統計データ検索 API",
      "source_ref": "PR01 PRCG20_2200000000"
    },
    {
      "as_of_date": "2022-11-01",
      "still_valid_2026": true,
      "retrieved_at": "2026-07-22",
      "veritas": "✅",
      "metric_id": "jp.cgpi.index",
      "industry_slug": "national",
      "industry_name_ja": "国内企業物価指数・総平均",
      "period": "2022-11",
      "period_type": "monthly",
      "value": 119.2,
      "unit": "index_2020=100",
      "source": "日銀 時系列統計データ検索 API",
      "source_ref": "PR01 PRCG20_2200000000"
    },
    {
      "as_of_date": "2022-12-01",
      "still_valid_2026": true,
      "retrieved_at": "2026-07-22",
      "veritas": "✅",
      "metric_id": "jp.cgpi.index",
      "industry_slug": "national",
      "industry_name_ja": "国内企業物価指数・総平均",
      "period": "2022-12",
      "period_type": "monthly",
      "value": 119.9,
      "unit": "index_2020=100",
      "source": "日銀 時系列統計データ検索 API",
      "source_ref": "PR01 PRCG20_2200000000"
    },
    {
      "as_of_date": "2023-01-01",
      "still_valid_2026": true,
      "retrieved_at": "2026-07-22",
      "veritas": "✅",
      "metric_id": "jp.cgpi.index",
      "industry_slug": "national",
      "industry_name_ja": "国内企業物価指数・総平均",
      "period": "2023-01",
      "period_type": "monthly",
      "value": 120.0,
      "unit": "index_2020=100",
      "source": "日銀 時系列統計データ検索 API",
      "source_ref": "PR01 PRCG20_2200000000"
    },
    {
      "as_of_date": "2023-02-01",
      "still_valid_2026": true,
      "retrieved_at": "2026-07-22",
      "veritas": "✅",
      "metric_id": "jp.cgpi.index",
      "industry_slug": "national",
      "industry_name_ja": "国内企業物価指数・総平均",
      "period": "2023-02",
      "period_type": "monthly",
      "value": 119.7,
      "unit": "index_2020=100",
      "source": "日銀 時系列統計データ検索 API",
      "source_ref": "PR01 PRCG20_2200000000"
    },
    {
      "as_of_date": "2023-03-01",
      "still_valid_2026": true,
      "retrieved_at": "2026-07-22",
      "veritas": "✅",
      "metric_id": "jp.cgpi.index",
      "industry_slug": "national",
      "industry_name_ja": "国内企業物価指数・総平均",
      "period": "2023-03",
      "period_type": "monthly",
      "value": 119.8,
      "unit": "index_2020=100",
      "source": "日銀 時系列統計データ検索 API",
      "source_ref": "PR01 PRCG20_2200000000"
    },
    {
      "as_of_date": "2023-04-01",
      "still_valid_2026": true,
      "retrieved_at": "2026-07-22",
      "veritas": "✅",
      "metric_id": "jp.cgpi.index",
      "industry_slug": "national",
      "industry_name_ja": "国内企業物価指数・総平均",
      "period": "2023-04",
      "period_type": "monthly",
      "value": 120.4,
      "unit": "index_2020=100",
      "source": "日銀 時系列統計データ検索 API",
      "source_ref": "PR01 PRCG20_2200000000"
    },
    {
      "as_of_date": "2023-05-01",
      "still_valid_2026": true,
      "retrieved_at": "2026-07-22",
      "veritas": "✅",
      "metric_id": "jp.cgpi.index",
      "industry_slug": "national",
      "industry_name_ja": "国内企業物価指数・総平均",
      "period": "2023-05",
      "period_type": "monthly",
      "value": 119.6,
      "unit": "index_2020=100",
      "source": "日銀 時系列統計データ検索 API",
      "source_ref": "PR01 PRCG20_2200000000"
    },
    {
      "as_of_date": "2023-06-01",
      "still_valid_2026": true,
      "retrieved_at": "2026-07-22",
      "veritas": "✅",
      "metric_id": "jp.cgpi.index",
      "industry_slug": "national",
      "industry_name_ja": "国内企業物価指数・総平均",
      "period": "2023-06",
      "period_type": "monthly",
      "value": 119.6,
      "unit": "index_2020=100",
      "source": "日銀 時系列統計データ検索 API",
      "source_ref": "PR01 PRCG20_2200000000"
    },
    {
      "as_of_date": "2023-07-01",
      "still_valid_2026": true,
      "retrieved_at": "2026-07-22",
      "veritas": "✅",
      "metric_id": "jp.cgpi.index",
      "industry_slug": "national",
      "industry_name_ja": "国内企業物価指数・総平均",
      "period": "2023-07",
      "period_type": "monthly",
      "value": 119.7,
      "unit": "index_2020=100",
      "source": "日銀 時系列統計データ検索 API",
      "source_ref": "PR01 PRCG20_2200000000"
    },
    {
      "as_of_date": "2023-08-01",
      "still_valid_2026": true,
      "retrieved_at": "2026-07-22",
      "veritas": "✅",
      "metric_id": "jp.cgpi.index",
      "industry_slug": "national",
      "industry_name_ja": "国内企業物価指数・総平均",
      "period": "2023-08",
      "period_type": "monthly",
      "value": 120.0,
      "unit": "index_2020=100",
      "source": "日銀 時系列統計データ検索 API",
      "source_ref": "PR01 PRCG20_2200000000"
    },
    {
      "as_of_date": "2023-09-01",
      "still_valid_2026": true,
      "retrieved_at": "2026-07-22",
      "veritas": "✅",
      "metric_id": "jp.cgpi.index",
      "industry_slug": "national",
      "industry_name_ja": "国内企業物価指数・総平均",
      "period": "2023-09",
      "period_type": "monthly",
      "value": 119.8,
      "unit": "index_2020=100",
      "source": "日銀 時系列統計データ検索 API",
      "source_ref": "PR01 PRCG20_2200000000"
    },
    {
      "as_of_date": "2023-10-01",
      "still_valid_2026": true,
      "retrieved_at": "2026-07-22",
      "veritas": "✅",
      "metric_id": "jp.cgpi.index",
      "industry_slug": "national",
      "industry_name_ja": "国内企業物価指数・総平均",
      "period": "2023-10",
      "period_type": "monthly",
      "value": 119.6,
      "unit": "index_2020=100",
      "source": "日銀 時系列統計データ検索 API",
      "source_ref": "PR01 PRCG20_2200000000"
    },
    {
      "as_of_date": "2023-11-01",
      "still_valid_2026": true,
      "retrieved_at": "2026-07-22",
      "veritas": "✅",
      "metric_id": "jp.cgpi.index",
      "industry_slug": "national",
      "industry_name_ja": "国内企業物価指数・総平均",
      "period": "2023-11",
      "period_type": "monthly",
      "value": 119.9,
      "unit": "index_2020=100",
      "source": "日銀 時系列統計データ検索 API",
      "source_ref": "PR01 PRCG20_2200000000"
    },
    {
      "as_of_date": "2023-12-01",
      "still_valid_2026": true,
      "retrieved_at": "2026-07-22",
      "veritas": "✅",
      "metric_id": "jp.cgpi.index",
      "industry_slug": "national",
      "industry_name_ja": "国内企業物価指数・総平均",
      "period": "2023-12",
      "period_type": "monthly",
      "value": 120.2,
      "unit": "index_2020=100",
      "source": "日銀 時系列統計データ検索 API",
      "source_ref": "PR01 PRCG20_2200000000"
    },
    {
      "as_of_date": "2024-01-01",
      "still_valid_2026": true,
      "retrieved_at": "2026-07-22",
      "veritas": "✅",
      "metric_id": "jp.cgpi.index",
      "industry_slug": "national",
      "industry_name_ja": "国内企業物価指数・総平均",
      "period": "2024-01",
      "period_type": "monthly",
      "value": 120.4,
      "unit": "index_2020=100",
      "source": "日銀 時系列統計データ検索 API",
      "source_ref": "PR01 PRCG20_2200000000"
    },
    {
      "as_of_date": "2024-02-01",
      "still_valid_2026": true,
      "retrieved_at": "2026-07-22",
      "veritas": "✅",
      "metric_id": "jp.cgpi.index",
      "industry_slug": "national",
      "industry_name_ja": "国内企業物価指数・総平均",
      "period": "2024-02",
      "period_type": "monthly",
      "value": 120.6,
      "unit": "index_2020=100",
      "source": "日銀 時系列統計データ検索 API",
      "source_ref": "PR01 PRCG20_2200000000"
    },
    {
      "as_of_date": "2024-03-01",
      "still_valid_2026": true,
      "retrieved_at": "2026-07-22",
      "veritas": "✅",
      "metric_id": "jp.cgpi.index",
      "industry_slug": "national",
      "industry_name_ja": "国内企業物価指数・総平均",
      "period": "2024-03",
      "period_type": "monthly",
      "value": 121.0,
      "unit": "index_2020=100",
      "source": "日銀 時系列統計データ検索 API",
      "source_ref": "PR01 PRCG20_2200000000"
    },
    {
      "as_of_date": "2024-04-01",
      "still_valid_2026": true,
      "retrieved_at": "2026-07-22",
      "veritas": "✅",
      "metric_id": "jp.cgpi.index",
      "industry_slug": "national",
      "industry_name_ja": "国内企業物価指数・総平均",
      "period": "2024-04",
      "period_type": "monthly",
      "value": 121.8,
      "unit": "index_2020=100",
      "source": "日銀 時系列統計データ検索 API",
      "source_ref": "PR01 PRCG20_2200000000"
    },
    {
      "as_of_date": "2024-05-01",
      "still_valid_2026": true,
      "retrieved_at": "2026-07-22",
      "veritas": "✅",
      "metric_id": "jp.cgpi.index",
      "industry_slug": "national",
      "industry_name_ja": "国内企業物価指数・総平均",
      "period": "2024-05",
      "period_type": "monthly",
      "value": 122.7,
      "unit": "index_2020=100",
      "source": "日銀 時系列統計データ検索 API",
      "source_ref": "PR01 PRCG20_2200000000"
    },
    {
      "as_of_date": "2024-06-01",
      "still_valid_2026": true,
      "retrieved_at": "2026-07-22",
      "veritas": "✅",
      "metric_id": "jp.cgpi.index",
      "industry_slug": "national",
      "industry_name_ja": "国内企業物価指数・総平均",
      "period": "2024-06",
      "period_type": "monthly",
      "value": 123.0,
      "unit": "index_2020=100",
      "source": "日銀 時系列統計データ検索 API",
      "source_ref": "PR01 PRCG20_2200000000"
    },
    {
      "as_of_date": "2024-07-01",
      "still_valid_2026": true,
      "retrieved_at": "2026-07-22",
      "veritas": "✅",
      "metric_id": "jp.cgpi.index",
      "industry_slug": "national",
      "industry_name_ja": "国内企業物価指数・総平均",
      "period": "2024-07",
      "period_type": "monthly",
      "value": 123.6,
      "unit": "index_2020=100",
      "source": "日銀 時系列統計データ検索 API",
      "source_ref": "PR01 PRCG20_2200000000"
    },
    {
      "as_of_date": "2024-08-01",
      "still_valid_2026": true,
      "retrieved_at": "2026-07-22",
      "veritas": "✅",
      "metric_id": "jp.cgpi.index",
      "industry_slug": "national",
      "industry_name_ja": "国内企業物価指数・総平均",
      "period": "2024-08",
      "period_type": "monthly",
      "value": 123.2,
      "unit": "index_2020=100",
      "source": "日銀 時系列統計データ検索 API",
      "source_ref": "PR01 PRCG20_2200000000"
    },
    {
      "as_of_date": "2024-09-01",
      "still_valid_2026": true,
      "retrieved_at": "2026-07-22",
      "veritas": "✅",
      "metric_id": "jp.cgpi.index",
      "industry_slug": "national",
      "industry_name_ja": "国内企業物価指数・総平均",
      "period": "2024-09",
      "period_type": "monthly",
      "value": 123.6,
      "unit": "index_2020=100",
      "source": "日銀 時系列統計データ検索 API",
      "source_ref": "PR01 PRCG20_2200000000"
    },
    {
      "as_of_date": "2024-10-01",
      "still_valid_2026": true,
      "retrieved_at": "2026-07-22",
      "veritas": "✅",
      "metric_id": "jp.cgpi.index",
      "industry_slug": "national",
      "industry_name_ja": "国内企業物価指数・総平均",
      "period": "2024-10",
      "period_type": "monthly",
      "value": 124.2,
      "unit": "index_2020=100",
      "source": "日銀 時系列統計データ検索 API",
      "source_ref": "PR01 PRCG20_2200000000"
    },
    {
      "as_of_date": "2024-11-01",
      "still_valid_2026": true,
      "retrieved_at": "2026-07-22",
      "veritas": "✅",
      "metric_id": "jp.cgpi.index",
      "industry_slug": "national",
      "industry_name_ja": "国内企業物価指数・総平均",
      "period": "2024-11",
      "period_type": "monthly",
      "value": 124.6,
      "unit": "index_2020=100",
      "source": "日銀 時系列統計データ検索 API",
      "source_ref": "PR01 PRCG20_2200000000"
    },
    {
      "as_of_date": "2024-12-01",
      "still_valid_2026": true,
      "retrieved_at": "2026-07-22",
      "veritas": "✅",
      "metric_id": "jp.cgpi.index",
      "industry_slug": "national",
      "industry_name_ja": "国内企業物価指数・総平均",
      "period": "2024-12",
      "period_type": "monthly",
      "value": 125.1,
      "unit": "index_2020=100",
      "source": "日銀 時系列統計データ検索 API",
      "source_ref": "PR01 PRCG20_2200000000"
    },
    {
      "as_of_date": "2025-01-01",
      "still_valid_2026": true,
      "retrieved_at": "2026-07-22",
      "veritas": "✅",
      "metric_id": "jp.cgpi.index",
      "industry_slug": "national",
      "industry_name_ja": "国内企業物価指数・総平均",
      "period": "2025-01",
      "period_type": "monthly",
      "value": 125.5,
      "unit": "index_2020=100",
      "source": "日銀 時系列統計データ検索 API",
      "source_ref": "PR01 PRCG20_2200000000"
    },
    {
      "as_of_date": "2025-02-01",
      "still_valid_2026": true,
      "retrieved_at": "2026-07-22",
      "veritas": "✅",
      "metric_id": "jp.cgpi.index",
      "industry_slug": "national",
      "industry_name_ja": "国内企業物価指数・総平均",
      "period": "2025-02",
      "period_type": "monthly",
      "value": 125.8,
      "unit": "index_2020=100",
      "source": "日銀 時系列統計データ検索 API",
      "source_ref": "PR01 PRCG20_2200000000"
    },
    {
      "as_of_date": "2025-03-01",
      "still_valid_2026": true,
      "retrieved_at": "2026-07-22",
      "veritas": "✅",
      "metric_id": "jp.cgpi.index",
      "industry_slug": "national",
      "industry_name_ja": "国内企業物価指数・総平均",
      "period": "2025-03",
      "period_type": "monthly",
      "value": 126.2,
      "unit": "index_2020=100",
      "source": "日銀 時系列統計データ検索 API",
      "source_ref": "PR01 PRCG20_2200000000"
    },
    {
      "as_of_date": "2025-04-01",
      "still_valid_2026": true,
      "retrieved_at": "2026-07-22",
      "veritas": "✅",
      "metric_id": "jp.cgpi.index",
      "industry_slug": "national",
      "industry_name_ja": "国内企業物価指数・総平均",
      "period": "2025-04",
      "period_type": "monthly",
      "value": 126.6,
      "unit": "index_2020=100",
      "source": "日銀 時系列統計データ検索 API",
      "source_ref": "PR01 PRCG20_2200000000"
    },
    {
      "as_of_date": "2025-05-01",
      "still_valid_2026": true,
      "retrieved_at": "2026-07-22",
      "veritas": "✅",
      "metric_id": "jp.cgpi.index",
      "industry_slug": "national",
      "industry_name_ja": "国内企業物価指数・総平均",
      "period": "2025-05",
      "period_type": "monthly",
      "value": 126.5,
      "unit": "index_2020=100",
      "source": "日銀 時系列統計データ検索 API",
      "source_ref": "PR01 PRCG20_2200000000"
    },
    {
      "as_of_date": "2025-06-01",
      "still_valid_2026": true,
      "retrieved_at": "2026-07-22",
      "veritas": "✅",
      "metric_id": "jp.cgpi.index",
      "industry_slug": "national",
      "industry_name_ja": "国内企業物価指数・総平均",
      "period": "2025-06",
      "period_type": "monthly",
      "value": 126.4,
      "unit": "index_2020=100",
      "source": "日銀 時系列統計データ検索 API",
      "source_ref": "PR01 PRCG20_2200000000"
    },
    {
      "as_of_date": "2025-07-01",
      "still_valid_2026": true,
      "retrieved_at": "2026-07-22",
      "veritas": "✅",
      "metric_id": "jp.cgpi.index",
      "industry_slug": "national",
      "industry_name_ja": "国内企業物価指数・総平均",
      "period": "2025-07",
      "period_type": "monthly",
      "value": 126.7,
      "unit": "index_2020=100",
      "source": "日銀 時系列統計データ検索 API",
      "source_ref": "PR01 PRCG20_2200000000"
    },
    {
      "as_of_date": "2025-08-01",
      "still_valid_2026": true,
      "retrieved_at": "2026-07-22",
      "veritas": "✅",
      "metric_id": "jp.cgpi.index",
      "industry_slug": "national",
      "industry_name_ja": "国内企業物価指数・総平均",
      "period": "2025-08",
      "period_type": "monthly",
      "value": 126.4,
      "unit": "index_2020=100",
      "source": "日銀 時系列統計データ検索 API",
      "source_ref": "PR01 PRCG20_2200000000"
    },
    {
      "as_of_date": "2025-09-01",
      "still_valid_2026": true,
      "retrieved_at": "2026-07-22",
      "veritas": "✅",
      "metric_id": "jp.cgpi.index",
      "industry_slug": "national",
      "industry_name_ja": "国内企業物価指数・総平均",
      "period": "2025-09",
      "period_type": "monthly",
      "value": 127.0,
      "unit": "index_2020=100",
      "source": "日銀 時系列統計データ検索 API",
      "source_ref": "PR01 PRCG20_2200000000"
    },
    {
      "as_of_date": "2025-10-01",
      "still_valid_2026": true,
      "retrieved_at": "2026-07-22",
      "veritas": "✅",
      "metric_id": "jp.cgpi.index",
      "industry_slug": "national",
      "industry_name_ja": "国内企業物価指数・総平均",
      "period": "2025-10",
      "period_type": "monthly",
      "value": 127.6,
      "unit": "index_2020=100",
      "source": "日銀 時系列統計データ検索 API",
      "source_ref": "PR01 PRCG20_2200000000"
    },
    {
      "as_of_date": "2025-11-01",
      "still_valid_2026": true,
      "retrieved_at": "2026-07-22",
      "veritas": "✅",
      "metric_id": "jp.cgpi.index",
      "industry_slug": "national",
      "industry_name_ja": "国内企業物価指数・総平均",
      "period": "2025-11",
      "period_type": "monthly",
      "value": 128.0,
      "unit": "index_2020=100",
      "source": "日銀 時系列統計データ検索 API",
      "source_ref": "PR01 PRCG20_2200000000"
    },
    {
      "as_of_date": "2025-12-01",
      "still_valid_2026": true,
      "retrieved_at": "2026-07-22",
      "veritas": "✅",
      "metric_id": "jp.cgpi.index",
      "industry_slug": "national",
      "industry_name_ja": "国内企業物価指数・総平均",
      "period": "2025-12",
      "period_type": "monthly",
      "value": 128.1,
      "unit": "index_2020=100",
      "source": "日銀 時系列統計データ検索 API",
      "source_ref": "PR01 PRCG20_2200000000"
    },
    {
      "as_of_date": "2026-01-01",
      "still_valid_2026": true,
      "retrieved_at": "2026-07-22",
      "veritas": "✅",
      "metric_id": "jp.cgpi.index",
      "industry_slug": "national",
      "industry_name_ja": "国内企業物価指数・総平均",
      "period": "2026-01",
      "period_type": "monthly",
      "value": 128.5,
      "unit": "index_2020=100",
      "source": "日銀 時系列統計データ検索 API",
      "source_ref": "PR01 PRCG20_2200000000"
    },
    {
      "as_of_date": "2026-02-01",
      "still_valid_2026": true,
      "retrieved_at": "2026-07-22",
      "veritas": "✅",
      "metric_id": "jp.cgpi.index",
      "industry_slug": "national",
      "industry_name_ja": "国内企業物価指数・総平均",
      "period": "2026-02",
      "period_type": "monthly",
      "value": 128.5,
      "unit": "index_2020=100",
      "source": "日銀 時系列統計データ検索 API",
      "source_ref": "PR01 PRCG20_2200000000"
    },
    {
      "as_of_date": "2026-03-01",
      "still_valid_2026": true,
      "retrieved_at": "2026-07-22",
      "veritas": "✅",
      "metric_id": "jp.cgpi.index",
      "industry_slug": "national",
      "industry_name_ja": "国内企業物価指数・総平均",
      "period": "2026-03",
      "period_type": "monthly",
      "value": 129.8,
      "unit": "index_2020=100",
      "source": "日銀 時系列統計データ検索 API",
      "source_ref": "PR01 PRCG20_2200000000"
    },
    {
      "as_of_date": "2026-04-01",
      "still_valid_2026": true,
      "retrieved_at": "2026-07-22",
      "veritas": "✅",
      "metric_id": "jp.cgpi.index",
      "industry_slug": "national",
      "industry_name_ja": "国内企業物価指数・総平均",
      "period": "2026-04",
      "period_type": "monthly",
      "value": 133.4,
      "unit": "index_2020=100",
      "source": "日銀 時系列統計データ検索 API",
      "source_ref": "PR01 PRCG20_2200000000"
    },
    {
      "as_of_date": "2026-05-01",
      "still_valid_2026": true,
      "retrieved_at": "2026-07-22",
      "veritas": "✅",
      "metric_id": "jp.cgpi.index",
      "industry_slug": "national",
      "industry_name_ja": "国内企業物価指数・総平均",
      "period": "2026-05",
      "period_type": "monthly",
      "value": 134.9,
      "unit": "index_2020=100",
      "source": "日銀 時系列統計データ検索 API",
      "source_ref": "PR01 PRCG20_2200000000"
    },
    {
      "as_of_date": "2026-06-01",
      "still_valid_2026": true,
      "retrieved_at": "2026-07-22",
      "veritas": "✅",
      "metric_id": "jp.cgpi.index",
      "industry_slug": "national",
      "industry_name_ja": "国内企業物価指数・総平均",
      "period": "2026-06",
      "period_type": "monthly",
      "value": 135.4,
      "unit": "index_2020=100",
      "source": "日銀 時系列統計データ検索 API",
      "source_ref": "PR01 PRCG20_2200000000"
    }
  ]
}
